federated_survival/__init__.py
federated_survival/core/__init__.py
federated_survival/core/augmenter.py
federated_survival/core/client.py
federated_survival/core/config.py
federated_survival/core/differential_privacy.py
federated_survival/core/mvae.py
federated_survival/core/runner.py
federated_survival/core/server.py
federated_survival/data/__init__.py
federated_survival/data/generator.py
federated_survival/data/loader.py
federated_survival/data/splitter.py
federated_survival/examples/basic_usage_example.py
federated_survival/examples/data_augmentation_example.py
federated_survival/examples/data_generation_example.py
federated_survival/examples/data_partitioning_example.py
federated_survival/examples/differential_privacy_example.py
federated_survival/examples/dp_mechanisms_comparison_example.py
federated_survival/examples/model_comparison_example.py
federated_survival/examples/privacy_comparison_example.py
federated_survival/utils/__init__.py
federated_survival/utils/metrics.py
federated_survival-0.5.0.dist-info/LICENSE
federated_survival-0.5.0.dist-info/METADATA
federated_survival-0.5.0.dist-info/WHEEL
federated_survival-0.5.0.dist-info/top_level.txt
federated_survival-0.5.0.dist-info/RECORD
