Metadata-Version: 2.1
Name: federated-survival
Version: 0.5.0
Summary: A federated learning framework for survival analysis with differential privacy support
Home-page: https://github.com/Amberwang12/federated-survival
Author: Wenjun Wang
Author-email: Wenjun Wang <amber930422@163.com>
Maintainer-email: Wenjun Wang <amber930422@163.com>
License: MIT
Project-URL: Homepage, https://github.com/Amberwang12/federated-survival
Project-URL: Documentation, https://github.com/Amberwang12/federated-survival#readme
Project-URL: Repository, https://github.com/Amberwang12/federated-survival
Project-URL: Bug Tracker, https://github.com/Amberwang12/federated-survival/issues
Keywords: federated learning,survival analysis,differential privacy,machine learning,healthcare
Classifier: Development Status :: 4 - Beta
Classifier: Intended Audience :: Developers
Classifier: Intended Audience :: Science/Research
Classifier: License :: OSI Approved :: MIT License
Classifier: Operating System :: OS Independent
Classifier: Programming Language :: Python :: 3
Classifier: Programming Language :: Python :: 3.8
Classifier: Programming Language :: Python :: 3.9
Classifier: Programming Language :: Python :: 3.10
Classifier: Programming Language :: Python :: 3.11
Classifier: Topic :: Scientific/Engineering :: Artificial Intelligence
Classifier: Topic :: Scientific/Engineering :: Medical Science Apps.
Requires-Python: >=3.8
License-File: LICENSE
Requires-Dist: numpy>=1.24.0
Requires-Dist: pandas>=2.0.0
Requires-Dist: torch>=2.0.0
Requires-Dist: scikit-learn>=1.3.0
Requires-Dist: sklearn-pandas>=2.2.0
Requires-Dist: lifelines>=0.27.0
Requires-Dist: pycox>=0.3.0
Requires-Dist: matplotlib>=3.7.0
Requires-Dist: scipy>=1.10.0
Requires-Dist: tqdm>=4.60.0
Requires-Dist: torchtuples>=0.2.0
Provides-Extra: dev
Requires-Dist: pytest>=7.0.0; extra == "dev"
Requires-Dist: pytest-cov>=4.0.0; extra == "dev"
Requires-Dist: black>=23.0.0; extra == "dev"
Requires-Dist: flake8>=6.0.0; extra == "dev"
Requires-Dist: mypy>=1.0.0; extra == "dev"
Provides-Extra: docs
Requires-Dist: sphinx>=5.0.0; extra == "docs"
Requires-Dist: sphinx-rtd-theme>=1.2.0; extra == "docs"
